{
    "Fri Nov 15 2024": {
        "Name": "Фулл-боди",
        "Упражнение1": [
            0,
            0,
            0
        ],
        "Упражнение2": [
            0,
            0,
            0
        ],
        "Упражнение3": [
            0,
            0,
            0
        ]
    },
    "Fri Nov 8 2024": {
        "Name": "Разминка",
        "Восемь": [
            2,
            2,
            3
        ],
        "Пять": [
            4,
            4,
            44
        ],
        "Раз": [
            4,
            4,
            4
        ],
        "Три": [
            4,
            4
        ]
    },
    "Thu Nov 7 2024": {
        "Name": "Кардио",
        "Два": [
            2,
            2
        ],
        "Один": [
            3
        ]
    }
}
